secreta/__init__.py
secreta/commands.py
secreta/constants.py
secreta/utils.py
secreta-0.0.1.dist-info/LICENSE.md
secreta-0.0.1.dist-info/METADATA
secreta-0.0.1.dist-info/WHEEL
secreta-0.0.1.dist-info/entry_points.txt
secreta-0.0.1.dist-info/RECORD
