Metadata-Version: 2.1
Name: secreta
Version: 0.0.1
Summary: 
Author: caiopeternela
Author-email: caiopeternela.dev@gmail.com
Requires-Python: >=3.8,<4.0
Classifier: Programming Language :: Python :: 3
Classifier: Programming Language :: Python :: 3.8
Classifier: Programming Language :: Python :: 3.9
Classifier: Programming Language :: Python :: 3.10
Classifier: Programming Language :: Python :: 3.11
Requires-Dist: cryptography (>=40.0.1,<41.0.0)
Requires-Dist: typer (>=0.7.0,<0.8.0)
